preprocessorAH/__init__.py
preprocessorAH/preprocessor.py
preprocessorAH-0.0.1.dist-info/LICENSE
preprocessorAH-0.0.1.dist-info/METADATA
preprocessorAH-0.0.1.dist-info/WHEEL
preprocessorAH-0.0.1.dist-info/top_level.txt
preprocessorAH-0.0.1.dist-info/RECORD
