Metadata-Version: 2.1
Name: preprocessorAH
Version: 0.0.1
Summary: preprocessorAH  Package for data pre-processing in Python
Home-page: https://github.com/anupamhore/PythonDataPreprocessor.git
Author: Anupam Hore
Author-email: anupam.hore@yahoo.com
License: UNKNOWN
Project-URL: Bug Tracker, https://github.com/anupamhore/PythonDataPreprocessor/issues
Platform: UNKNOWN
Classifier: Programming Language :: Python :: 3
Classifier: License :: OSI Approved :: MIT License
Classifier: Operating System :: OS Independent
Requires-Python: >=3.8
Requires-Dist: statsmodels (>=0.12.0)
Requires-Dist: pandas (>=0.25.3)
Requires-Dist: scikit-learn (>=0.24.2)
